Changelog.txt
LICENSE.txt
MANIFEST.in
README.rst
requirements.txt
setup.py
oschameleon/SIMATIC_300_PLC.txt
oschameleon/__init__.py
oschameleon/osfuscation.py
oschameleon/parse_fp.py
oschameleon.egg-info/PKG-INFO
oschameleon.egg-info/SOURCES.txt
oschameleon.egg-info/dependency_links.txt
oschameleon.egg-info/not-zip-safe
oschameleon.egg-info/requires.txt
oschameleon.egg-info/top_level.txt
samples/__init__.py
samples/root_fork.py