Metadata-Version: 1.1
Name: oschameleon
Version: 0.1.2
Summary: OS Fingerprint Obfuscation for modern Linux Kernels
Home-page: https://github.com/glastopf/oschameleon
Author: Glastopf Project
Author-email: glaslos@gmail.com
License: UNKNOWN
Platform: UNKNOWN
Classifier: Development Status :: 4 - Beta
Classifier: Environment :: Console
Classifier: Intended Audience :: Developers
Classifier: License :: OSI Approved :: MIT License
Classifier: Operating System :: POSIX :: Linux
Classifier: Programming Language :: Python
Classifier: Topic :: Security
